pgbedrock/__init__.py
pgbedrock/attributes.py
pgbedrock/cli.py
pgbedrock/common.py
pgbedrock/context.py
pgbedrock/core_configure.py
pgbedrock/core_generate.py
pgbedrock/memberships.py
pgbedrock/ownerships.py
pgbedrock/privileges.py
pgbedrock/spec_inspector.py
pgbedrock-0.4.2.dist-info/LICENSE
pgbedrock-0.4.2.dist-info/METADATA
pgbedrock-0.4.2.dist-info/WHEEL
pgbedrock-0.4.2.dist-info/entry_points.txt
pgbedrock-0.4.2.dist-info/top_level.txt
pgbedrock-0.4.2.dist-info/RECORD
