Metadata-Version: 2.1
Name: pgbedrock
Version: 0.4.2
Summary: Manage Postgres roles and privileges
Home-page: https://github.com/Squarespace/pgbedrock
Author: Squarespace Data Engineering
Author-email: UNKNOWN
License: Apache License 2.0
Download-URL: https://github.com/Squarespace/pgbedrock/tarball/0.4.2
Platform: UNKNOWN
Classifier: Programming Language :: Python
Classifier: Programming Language :: Python :: 2
Classifier: Programming Language :: Python :: 3
Classifier: Programming Language :: Python :: 2.7
Classifier: Programming Language :: Python :: 3.6
Requires-Dist: Cerberus
Requires-Dist: click
Requires-Dist: Jinja2
Requires-Dist: psycopg2
Requires-Dist: PyYAML
